stringindexer.py
PrettyIndexer-0.0.6.dist-info/METADATA
PrettyIndexer-0.0.6.dist-info/WHEEL
PrettyIndexer-0.0.6.dist-info/top_level.txt
PrettyIndexer-0.0.6.dist-info/RECORD
