Metadata-Version: 2.1
Name: PrettyIndexer
Version: 0.0.6
Summary: Get positive and negative index values of a string displayed in a beautiful manner.
Home-page: https://github.com/ahn1305/PrettyIndexer
Author: Ashwin.B
Author-email: ahnashwin1305@gmail.com
License: MIT
Platform: UNKNOWN
Classifier: Programming Language :: Python :: 3.6
Classifier: Programming Language :: Python :: 3.7
Classifier: Programming Language :: Python :: 3.8
Classifier: License :: OSI Approved :: MIT License
Classifier: Operating System :: OS Independent
